<?xml version="1.0"?>
<opencv_storage>
<cascade>
  <stageType>BOOST</stageType>
  <featureType>HAAR</featureType>
  <height>16</height>
  <width>32</width>
  <stageParams>
    <boostType>GAB</boostType>
    <minHitRate>9.4999998807907104e-01</minHitRate>
    <maxFalseAlarm>2.0000000298023224e-01</maxFalseAlarm>
    <weightTrimRate>3.4999999403953552e-01</weightTrimRate>
    <maxDepth>1</maxDepth>
    <maxWeakCount>80</maxWeakCount></stageParams>
  <featureParams>
    <maxCatCount>0</maxCatCount>
    <featSize>1</featSize>
    <mode>BASIC</mode></featureParams>
  <stageNum>1</stageNum>
  <stages>
    <!-- stage 0 -->
    <_>
      <maxWeakCount>2</maxWeakCount>
      <stageThreshold>-2.2858379781246185e-01</stageThreshold>
      <weakClassifiers>
        <_>
          <internalNodes>
            0 -1 0 1.8052467703819275e-01</internalNodes>
          <leafValues>
            -9.5114731788635254e-01 6.8120807409286499e-01</leafValues></_>
        <_>
          <internalNodes>
            0 -1 1 1.7734547145664692e-03</internalNodes>
          <leafValues>
            -9.0427964925765991e-01 7.2256350517272949e-01</leafValues></_></weakClassifiers></_></stages>
  <features>
    <_>
      <rects>
        <_>
          0 0 16 10 -1.</_>
        <_>
          8 0 8 10 2.</_></rects>
      <tilted>0</tilted></_>
    <_>
      <rects>
        <_>
          1 13 20 2 -1.</_>
        <_>
          11 13 10 2 2.</_></rects>
      <tilted>0</tilted></_></features></cascade>
</opencv_storage>
